hive/__init__.py
hive/discovery.py
hive/api/__init__.py
hive/api/app.py
hive/cli/__init__.py
hive/cli/__main__.py
hive/cli/create.py
hive/cli/create_ai.py
hive/cli/dev.py
hive/cli/init.py
hive/cli/version.py
hive/config/__init__.py
hive/config/builtin_tools.py
hive/config/defaults.py
hive/config/settings.py
hive/examples/agents/EXAMPLES_README.md
hive/examples/agents/QUICK_START.md
hive/examples/agents/create_and_test_agents.py
hive/examples/agents/demo_all_agents.py
hive/examples/agents/code-reviewer/README.md
hive/examples/agents/code-reviewer/agent.py
hive/examples/agents/code-reviewer/config.yaml
hive/examples/agents/researcher/README.md
hive/examples/agents/researcher/agent.py
hive/examples/agents/researcher/config.yaml
hive/examples/agents/support-bot/README.md
hive/examples/agents/support-bot/agent.py
hive/examples/agents/support-bot/config.yaml
hive/examples/teams/INDEX.md
hive/examples/teams/dev-team/README.md
hive/examples/teams/dev-team/config.yaml
hive/examples/teams/dev-team/team.py
hive/examples/teams/support-router/README.md
hive/examples/teams/support-router/config.yaml
hive/examples/teams/support-router/team.py
hive/examples/tools/csv_analyzer/README.md
hive/examples/tools/csv_analyzer/__init__.py
hive/examples/tools/csv_analyzer/config.yaml
hive/examples/tools/csv_analyzer/tool.py
hive/examples/tools/slack_notifier/README.md
hive/examples/tools/slack_notifier/__init__.py
hive/examples/tools/slack_notifier/config.yaml
hive/examples/tools/slack_notifier/tool.py
hive/examples/tools/web_search/README.md
hive/examples/tools/web_search/__init__.py
hive/examples/tools/web_search/config.yaml
hive/examples/tools/web_search/tool.py
hive/examples/workflows/parallel_workflow/README.md
hive/examples/workflows/parallel_workflow/__init__.py
hive/examples/workflows/parallel_workflow/config.yaml
hive/examples/workflows/parallel_workflow/workflow.py
hive/examples/workflows/research_workflow/README.md
hive/examples/workflows/research_workflow/__init__.py
automagik_hive-1.0.0rc6.dist-info/METADATA
automagik_hive-1.0.0rc6.dist-info/WHEEL
automagik_hive-1.0.0rc6.dist-info/entry_points.txt
automagik_hive-1.0.0rc6.dist-info/licenses/LICENSE
automagik_hive-1.0.0rc6.dist-info/RECORD
