Metadata-Version: 2.4
Name: automagik-hive
Version: 1.0.0rc6
Summary: Hive Agents - AI-powered scaffolding for Agno agents - YAML-first DevX layer
License-File: LICENSE
Requires-Python: >=3.11
Requires-Dist: agno>=2.2.3
Requires-Dist: aiosqlite>=0.21.0
Requires-Dist: anthropic>=0.64.0
Requires-Dist: fastapi>=0.116.1
Requires-Dist: greenlet>=3.2.4
Requires-Dist: httpx>=0.28.1
Requires-Dist: loguru>=0.7.3
Requires-Dist: openai>=1.101.0
Requires-Dist: pandas>=2.3.2
Requires-Dist: pgvector>=0.4.1
Requires-Dist: psycopg[binary,pool]>=3.2.9
Requires-Dist: pydantic-settings>=2.11.0
Requires-Dist: pydantic>=2.12.0
Requires-Dist: python-dotenv>=1.2.0
Requires-Dist: pyyaml>=6.0.3
Requires-Dist: rich>=14.2.0
Requires-Dist: sqlalchemy>=2.0.43
Requires-Dist: typer>=0.20.0
Requires-Dist: uvicorn[standard]>=0.35.0
Requires-Dist: watchdog>=6.0.0
